LICENSE
MANIFEST.in
README.md
VERSION
requirements.txt
setup.cfg
setup.py
dynamic_plugins/__init__.py
dynamic_plugins/dependencies.py
dynamic_plugins/exceptions.py
dynamic_plugins/extensions.py
dynamic_plugins.egg-info/PKG-INFO
dynamic_plugins.egg-info/SOURCES.txt
dynamic_plugins.egg-info/dependency_links.txt
dynamic_plugins.egg-info/requires.txt
dynamic_plugins.egg-info/top_level.txt
dynamic_plugins.egg-info/zip-safe