Metadata-Version: 2.1
Name: dynamic-plugins
Version: 1.0.9
Summary: Python plugin system with dynamic loading of plugins
Home-page: https://github.com/cr0hn/python-dynamic-plugins
Author: Daniel Garcia
Maintainer: Daniel Garcia (cr0hn)
Maintainer-email: cr0hn@cr0hn.com
License: License :: OSI Approved :: MIT License
Platform: UNKNOWN
Classifier: License :: OSI Approved :: MIT License
Classifier: Programming Language :: Python :: 3.10
Classifier: Programming Language :: Python :: 3.11
Classifier: Environment :: Console
Classifier: Operating System :: POSIX
Classifier: Operating System :: MacOS
Classifier: Operating System :: OS Independent
Classifier: Operating System :: Microsoft :: Windows
